slowtype
