Metadata-Version: 2.1
Name: slowtype
Version: 0.3
Summary: SlowType - Small python library for type-effect
Author-email: isgamekillerept@gmail.com
